evopt/__init__.py
evopt/base_optimiser.py
evopt/base_optimizer.py
evopt/cma_optimiser.py
evopt/cma_optimizer.py
evopt/directory_manager.py
evopt/loss.py
evopt/optimiser.py
evopt/optimizer.py
evopt/plotting.py
evopt/slurm_executor.py
evopt/utils.py
evopt-0.140.dist-info/LICENSE
evopt-0.140.dist-info/METADATA
evopt-0.140.dist-info/WHEEL
evopt-0.140.dist-info/top_level.txt
evopt-0.140.dist-info/RECORD
