Metadata-Version: 2.2
Name: evopt
Version: 0.140
Summary: User Friendly Data-Driven Numerical Optimization
Home-page: https://github.com/Robh96/Evopt
Author: Roberto Hart-Villamil
Author-email: Roberto Hart-Villamil <rob.hartvillamil@gmail.com>
License: GNU v3.0
Keywords: optimization,evolutionary,cmaes,calibration,simulation,fine-tuning,simple
Classifier: Programming Language :: Python :: 3
Classifier: License :: OSI Approved :: GNU General Public License v3 or later (GPLv3+)
Classifier: Operating System :: OS Independent
Requires-Python: >=3.10
License-File: LICENSE
Requires-Dist: numpy>=2.2.1
Requires-Dist: pandas>=2.2.3
Requires-Dist: cma>=4.0.0
Requires-Dist: cloudpickle>=3.1.1
Requires-Dist: scipy>=1.15.0
Requires-Dist: plotly>=5.24.1
Requires-Dist: matplotlib>=3.10.0
Dynamic: author
Dynamic: home-page
Dynamic: requires-python
